LICENSE.txt
README.rst
setup.py
pypdc/__init__.py
pypdc/_version.py
pypdc/adaptative.py
pypdc/analysis.py
pypdc/ar_data.py
pypdc/ar_fit.py
pypdc/asymp.py
pypdc/bootstrap.py
pypdc/plot_digraph.py
pypdc/plotting.py
pypdc/plotting_old.py
pypdc/utils.py
pypdc.egg-info/PKG-INFO
pypdc.egg-info/SOURCES.txt
pypdc.egg-info/dependency_links.txt
pypdc.egg-info/not-zip-safe
pypdc.egg-info/top_level.txt